VIIDS/GridSearchCV_&_K-FoldCV.py
VIIDS/__init__.py
VIIDS/graphing.py
VIIDS/random_forest.py
VIIDS/regression.py
VIIDS/setup.py
VIIDS-1.0.0.dist-info/METADATA
VIIDS-1.0.0.dist-info/WHEEL
VIIDS-1.0.0.dist-info/top_level.txt
VIIDS-1.0.0.dist-info/RECORD
