Metadata-Version: 2.1
Name: VIIDS
Version: 1.0.0
Summary: VII Data Science Internship bundle of useful functions
Author: VII Data Science
